porkbun_mcp/__init__.py
porkbun_mcp/config.py
porkbun_mcp/context.py
porkbun_mcp/errors.py
porkbun_mcp/models.py
porkbun_mcp/prompts/__init__.py
porkbun_mcp/prompts/dns.py
porkbun_mcp/server.py
porkbun_mcp/tools/__init__.py
porkbun_mcp/tools/dns.py
porkbun_mcp/tools/dnssec.py
porkbun_mcp/tools/domains.py
porkbun_mcp/tools/ping.py
porkbun_mcp/tools/pricing.py
porkbun_mcp/tools/ssl.py
porkbun_mcp-1.1.1.dist-info/WHEEL
porkbun_mcp-1.1.1.dist-info/entry_points.txt
porkbun_mcp-1.1.1.dist-info/METADATA
porkbun_mcp-1.1.1.dist-info/RECORD
