Metadata-Version: 2.4
Name: porkbun-mcp
Version: 1.1.1
Summary: MCP server for Porkbun DNS API
Keywords: mcp,porkbun,dns,model-context-protocol
Author: Major Hayden
Author-email: Major Hayden <major@mhtx.net>
License-Expression: MIT
Classifier: Development Status :: 5 - Production/Stable
Classifier: Intended Audience :: Developers
Classifier: License :: OSI Approved :: MIT License
Classifier: Programming Language :: Python :: 3.13
Classifier: Programming Language :: Python :: 3.14
Classifier: Topic :: Internet :: Name Service (DNS)
Classifier: Typing :: Typed
Requires-Dist: fastmcp>=3.0.0b1
Requires-Dist: oinker>=0.1.1
Requires-Dist: pydantic-settings>=2.0.0
Requires-Python: >=3.13
Project-URL: Homepage, https://github.com/major/porkbun-mcp
Project-URL: Repository, https://github.com/major/porkbun-mcp
